scembed/__init__.py
scembed/aggregation.py
scembed/check.py
scembed/evaluation.py
scembed/factory.py
scembed/logging.py
scembed/utils.py
scembed/methods/__init__.py
scembed/methods/base.py
scembed/methods/cpu_methods.py
scembed/methods/gpu_methods.py
scembed-0.1.1.dist-info/METADATA
scembed-0.1.1.dist-info/WHEEL
scembed-0.1.1.dist-info/licenses/LICENSE
scembed-0.1.1.dist-info/RECORD
