Metadata-Version: 2.4
Name: scembed
Version: 0.1.1
Summary: Run embedding comparisons for single-cell data
Project-URL: Documentation, https://scembed.readthedocs.io/
Project-URL: Homepage, https://github.com/quadbio/scembed
Project-URL: Source, https://github.com/quadbio/scembed
Author: Marius Lange
Maintainer-email: Marius Lange <mlange@ethz.ch>
License: MIT License
License-File: LICENSE
Classifier: Programming Language :: Python :: 3 :: Only
Classifier: Programming Language :: Python :: 3.11
Classifier: Programming Language :: Python :: 3.12
Classifier: Programming Language :: Python :: 3.13
Classifier: Programming Language :: Python :: 3.14
Requires-Python: >=3.11
Requires-Dist: numpy>=2.1
Requires-Dist: pyarrow>=21
Requires-Dist: scanpy>=1.11.4
Requires-Dist: scib-metrics>=0.5.6
Requires-Dist: scipy>=1.16
Requires-Dist: session-info2
Requires-Dist: wandb
Provides-Extra: all
Requires-Dist: faiss-gpu; extra == 'all'
Requires-Dist: harmony-pytorch; extra == 'all'
Requires-Dist: pyliger>=0.2.4; extra == 'all'
Requires-Dist: rapids-singlecell; extra == 'all'
Requires-Dist: scanorama>=1.7.4; extra == 'all'
Requires-Dist: scarches>=0.6.1; extra == 'all'
Requires-Dist: scvi-tools>=1.3; extra == 'all'
Requires-Dist: torch>=2.8; extra == 'all'
Provides-Extra: cpu
Requires-Dist: pyliger>=0.2.4; extra == 'cpu'
Requires-Dist: scanorama>=1.7.4; extra == 'cpu'
Provides-Extra: dev
Requires-Dist: pre-commit; extra == 'dev'
Requires-Dist: twine>=4.0.2; extra == 'dev'
Provides-Extra: doc
Requires-Dist: docutils!=0.18.*,!=0.19.*,>=0.8; extra == 'doc'
Requires-Dist: ipykernel; extra == 'doc'
Requires-Dist: ipython; extra == 'doc'
Requires-Dist: myst-nb>=1.1; extra == 'doc'
Requires-Dist: pandas; extra == 'doc'
Requires-Dist: setuptools; extra == 'doc'
Requires-Dist: sphinx-autodoc-typehints; extra == 'doc'
Requires-Dist: sphinx-book-theme>=1; extra == 'doc'
Requires-Dist: sphinx-copybutton; extra == 'doc'
Requires-Dist: sphinx-tabs; extra == 'doc'
Requires-Dist: sphinx>=8.1; extra == 'doc'
Requires-Dist: sphinxcontrib-bibtex>=1; extra == 'doc'
Requires-Dist: sphinxext-opengraph; extra == 'doc'
Provides-Extra: fast-metrics
Requires-Dist: faiss-gpu; extra == 'fast-metrics'
Requires-Dist: rapids-singlecell; extra == 'fast-metrics'
Provides-Extra: gpu
Requires-Dist: harmony-pytorch; extra == 'gpu'
Requires-Dist: scarches>=0.6.1; extra == 'gpu'
Requires-Dist: scvi-tools>=1.3; extra == 'gpu'
Requires-Dist: torch>=2.8; extra == 'gpu'
Provides-Extra: test
Requires-Dist: coverage>=7.10; extra == 'test'
Requires-Dist: h5py; extra == 'test'
Requires-Dist: harmony-pytorch; extra == 'test'
Requires-Dist: pyarrow; extra == 'test'
Requires-Dist: pyliger>=0.2.4; extra == 'test'
Requires-Dist: pytest; extra == 'test'
Requires-Dist: pytest-cov; extra == 'test'
Requires-Dist: scanorama>=1.7.4; extra == 'test'
Requires-Dist: scarches>=0.6.1; extra == 'test'
Requires-Dist: scvi-tools>=1.3; extra == 'test'
Requires-Dist: torch>=2.8; extra == 'test'
